quick/__init__.py
quick/backend/__init__.py
quick/backend/backend.py
quick/backend/qiskit_backends/aer_backend.py
quick/backend/qiskit_backends/fake_ibm_backend.py
quick/circuit/__init__.py
quick/circuit/circuit.py
quick/circuit/circuit_log_ignore.py
quick/circuit/circuit_utils.py
quick/circuit/cirqcircuit.py
quick/circuit/cudaqcircuit_ignore.py
quick/circuit/pennylanecircuit.py
quick/circuit/qiskitcircuit.py
quick/circuit/tketcircuit.py
quick/circuit/dag/__init__.py
quick/circuit/dag/dagcircuit.py
quick/circuit/dag/dagnode.py
quick/circuit/from_framework/__init__.py
quick/circuit/from_framework/from_cirq.py
quick/circuit/from_framework/from_framework.py
quick/circuit/from_framework/from_qasm_ignore.py
quick/circuit/from_framework/from_qiskit.py
quick/circuit/from_framework/from_tket.py
quick/circuit/gate_matrix/__init__.py
quick/circuit/gate_matrix/controlled_qubit_gates.py
quick/circuit/gate_matrix/gate.py
quick/circuit/gate_matrix/single_qubit_gates.py
quick/compiler/__init__.py
quick/compiler/compiler.py
quick/optimizer/__init__.py
quick/optimizer/optimizer.py
quick/optimizer/qiskit_transpiler.py
quick/optimizer/tket2optimizer.py
quick/predicates/__init__.py
quick/predicates/predicates.py
quick/primitives/__init__.py
quick/primitives/bra.py
quick/primitives/ket.py
quick/primitives/operator.py
quick/synthesis/__init__.py
quick/synthesis/gate_decompositions/__init__.py
quick/synthesis/gate_decompositions/one_qubit_decomposition.py
quick/synthesis/gate_decompositions/multi_controlled_decomposition/__init__.py
quick/synthesis/gate_decompositions/multi_controlled_decomposition/mcsu2_real_diagonal.py
quick/synthesis/gate_decompositions/multi_controlled_decomposition/mcx_utils.py
quick/synthesis/gate_decompositions/multi_controlled_decomposition/mcx_vchain.py
quick/synthesis/gate_decompositions/two_qubit_decomposition/two_qubit_decomposition.py
quick/synthesis/gate_decompositions/two_qubit_decomposition/weyl.py
quick/synthesis/statepreparation/__init__.py
quick_core-0.0.0rc0.dist-info/LICENSE
quick_core-0.0.0rc0.dist-info/METADATA
quick_core-0.0.0rc0.dist-info/WHEEL
quick_core-0.0.0rc0.dist-info/top_level.txt
quick_core-0.0.0rc0.dist-info/RECORD
