Metadata-Version: 2.2
Name: quick-core
Version: 0.0.0rc0
Summary: quick is an agnostic gate-based circuit SDK, providing an integrated interface for using any supported quantum circuit framework seamlessly.
Author-email: Amir Ali Malekani Nezhad <amiralimlk07@gmail.com>
Maintainer-email: Amir Ali Malekani Nezhad <amiralimlk07@gmail.com>
License:                                  Apache License
Project-URL: Repository, https://github.com/qualition/quick.git
Project-URL: Bug Tracker, https://github.com/qualition/quick/issues
Keywords: quantum computing,quantum circuit,quantum compiler
Classifier: Development Status :: 3 - Alpha
Classifier: Programming Language :: Python :: 3.10
Classifier: Programming Language :: Python :: 3.11
Classifier: Programming Language :: Python :: 3.12
Classifier: Operating System :: OS Independent
Requires-Python: <3.13,>=3.10
License-File: LICENSE
Requires-Dist: cirq-core==1.4.1
Requires-Dist: genQC==0.1.0
Requires-Dist: numpy<3.0,>=1.23
Requires-Dist: pennylane==0.39.0
Requires-Dist: pytket==1.37.0
Requires-Dist: pytket-qiskit==0.62.0
Requires-Dist: pytket-cirq==0.39.0
Requires-Dist: qiskit==1.3.1
Requires-Dist: qiskit_aer==0.16.0
Requires-Dist: qiskit_ibm_runtime==0.34.0
Requires-Dist: qiskit-transpiler-service==0.4.14
Requires-Dist: quimb==1.10.0
Requires-Dist: tket2==0.6.0
Provides-Extra: dev
Requires-Dist: ruff==0.9.2; extra == "dev"
Requires-Dist: mypy==1.14.1; extra == "dev"
Requires-Dist: pytest==8.3.4; extra == "dev"
Requires-Dist: pytest-mock==3.14.0; extra == "dev"
Requires-Dist: pytest-cov==6.0.0; extra == "dev"
Requires-Dist: coverage==7.6.10; extra == "dev"
